gitruck/flet_search_bar/__init__.py
gitruck/flet_search_bar/search_bar.py
gitruck/flet_search_bar/search_bar_style.py
gitruck_flet_search_bar-0.0.1.dist-info/LICENSE
gitruck_flet_search_bar-0.0.1.dist-info/METADATA
gitruck_flet_search_bar-0.0.1.dist-info/WHEEL
gitruck_flet_search_bar-0.0.1.dist-info/top_level.txt
gitruck_flet_search_bar-0.0.1.dist-info/RECORD
