Metadata-Version: 2.1
Name: gitruck-flet-search-bar
Version: 0.0.1
Summary: 基于Flet的搜索组件
Home-page: https://github.com/Gitruck/flet-search-bar
Author: Colsrch
Author-email: Colsrch <colsrch@foxmail.com>
License: Apache-2.0
Classifier: License :: OSI Approved :: MIT License
Classifier: Programming Language :: Python :: 3.9
Classifier: Programming Language :: Python :: 3.10
Classifier: Programming Language :: Python :: 3.11
Classifier: Operating System :: MacOS :: MacOS X
Classifier: Operating System :: Microsoft :: Windows
Requires-Python: >=3.9
License-File: LICENSE
Requires-Dist: flet >=0.9.0
